Workbook

Sheet Dashboard
A1: SALES ANALYTICS DASHBOARD
A2: Practice project • Sample transactions • Year 2025
A4: Total Revenue | C4: Total Orders | E4: Units Sold | G4: Avg. Revenue / Order
A5: =SUM('Sales Data'!J2:J301) | C5: =COUNTA('Sales Data'!A2:A301) | E5: =SUM('Sales Data'!G2:G301) | G5: =AVERAGE('Sales Data'!J2:J301)
A8: Revenue by Category | D8: Revenue by Region | G8: Monthly Revenue
A9: Category | B9: Revenue (₹) | D9: Region | E9: Revenue (₹) | G9: Month | H9: Revenue (₹)
A10: Accessories | B10: =SUMIF('Sales Data'!$F$2:$F$301,A10,'Sales Data'!$J$2:$J$301) | D10: West | E10: =SUMIF('Sales Data'!$D$2:$D$301,D10,'Sales Data'!$J$2:$J$301) | G10: Jan | H10: =SUMIFS('Sales Data'!$J$2:$J$301,'Sales Data'!$B$2:$B$301,">="&DATE(2025,1,1),'Sales Data'!$B$2:$B$301,"<"&DATE(2025,2,1))
A11: Electronics | B11: =SUMIF('Sales Data'!$F$2:$F$301,A11,'Sales Data'!$J$2:$J$301) | D11: North | E11: =SUMIF('Sales Data'!$D$2:$D$301,D11,'Sales Data'!$J$2:$J$301) | G11: Feb | H11: =SUMIFS('Sales Data'!$J$2:$J$301,'Sales Data'!$B$2:$B$301,">="&DATE(2025,2,1),'Sales Data'!$B$2:$B$301,"<"&DATE(2025,3,1))
A12: Furniture | B12: =SUMIF('Sales Data'!$F$2:$F$301,A12,'Sales Data'!$J$2:$J$301) | D12: South | E12: =SUMIF('Sales Data'!$D$2:$D$301,D12,'Sales Data'!$J$2:$J$301) | G12: Mar | H12: =SUMIFS('Sales Data'!$J$2:$J$301,'Sales Data'!$B$2:$B$301,">="&DATE(2025,3,1),'Sales Data'!$B$2:$B$301,"<"&DATE(2025,4,1))
A13: Stationery | B13: =SUMIF('Sales Data'!$F$2:$F$301,A13,'Sales Data'!$J$2:$J$301) | D13: East | E13: =SUMIF('Sales Data'!$D$2:$D$301,D13,'Sales Data'!$J$2:$J$301) | G13: Apr | H13: =SUMIFS('Sales Data'!$J$2:$J$301,'Sales Data'!$B$2:$B$301,">="&DATE(2025,4,1),'Sales Data'!$B$2:$B$301,"<"&DATE(2025,5,1))
G14: May | H14: =SUMIFS('Sales Data'!$J$2:$J$301,'Sales Data'!$B$2:$B$301,">="&DATE(2025,5,1),'Sales Data'!$B$2:$B$301,"<"&DATE(2025,6,1))
G15: Jun | H15: =SUMIFS('Sales Data'!$J$2:$J$301,'Sales Data'!$B$2:$B$301,">="&DATE(2025,6,1),'Sales Data'!$B$2:$B$301,"<"&DATE(2025,7,1))
G16: Jul | H16: =SUMIFS('Sales Data'!$J$2:$J$301,'Sales Data'!$B$2:$B$301,">="&DATE(2025,7,1),'Sales Data'!$B$2:$B$301,"<"&DATE(2025,8,1))
G17: Aug | H17: =SUMIFS('Sales Data'!$J$2:$J$301,'Sales Data'!$B$2:$B$301,">="&DATE(2025,8,1),'Sales Data'!$B$2:$B$301,"<"&DATE(2025,9,1))
G18: Sep | H18: =SUMIFS('Sales Data'!$J$2:$J$301,'Sales Data'!$B$2:$B$301,">="&DATE(2025,9,1),'Sales Data'!$B$2:$B$301,"<"&DATE(2025,10,1))
G19: Oct | H19: =SUMIFS('Sales Data'!$J$2:$J$301,'Sales Data'!$B$2:$B$301,">="&DATE(2025,10,1),'Sales Data'!$B$2:$B$301,"<"&DATE(2025,11,1))
G20: Nov | H20: =SUMIFS('Sales Data'!$J$2:$J$301,'Sales Data'!$B$2:$B$301,">="&DATE(2025,11,1),'Sales Data'!$B$2:$B$301,"<"&DATE(2025,12,1))
G21: Dec | H21: =SUMIFS('Sales Data'!$J$2:$J$301,'Sales Data'!$B$2:$B$301,">="&DATE(2025,12,1),'Sales Data'!$B$2:$B$301,"<"&DATE(2025,2026,1))

Sheet Sales Data
A1: Order ID | B1: Order Date | C1: City | D1: Region | E1: Product | F1: Category | G1: Quantity | H1: Unit Price (₹) | I1: Discount | J1: Revenue (₹) | K1: Sales Channel
A2: ORD0266 | B2: 45659 | C2: Mumbai | D2: West | E2: Office Chair | F2: Furniture | G2: 2 | H2: 8274.39 | I2: 0 | J2: 16548.78 | K2: Online
A3: ORD0223 | B3: 45659 | C3: Mumbai | D3: West | E3: USB Drive | F3: Accessories | G3: 7 | H3: 562.77 | I3: 0.15 | J3: 3348.48 | K3: Distributor
A4: ORD0126 | B4: 45661 | C4: Thane | D4: West | E4: USB Drive | F4: Accessories | G4: 7 | H4: 513.16 | I4: 0 | J4: 3592.12 | K4: Retail
A5: ORD0297 | B5: 45663 | C5: Mumbai | D5: North | E5: Headphones | F5: Electronics | G5: 8 | H5: 1938.58 | I5: 0.1 | J5: 13957.78 | K5: Retail
A6: ORD0160 | B6: 45665 | C6: Nashik | D6: East | E6: Headphones | F6: Electronics | G6: 7 | H6: 1875.92 | I6: 0 | J6: 13131.44 | K6: Distributor
A7: ORD0290 | B7: 45665 | C7: Pune | D7: North | E7: Monitor | F7: Electronics | G7: 2 | H7: 12520.23 | I7: 0.1 | J7: 22536.41 | K7: Retail
A8: ORD0122 | B8: 45668 | C8: Nagpur | D8: East | E8: Office Chair | F8: Furniture | G8: 3 | H8: 8062.05 | I8: 0 | J8: 24186.15 | K8: Retail
A9: ORD0253 | B9: 45668 | C9: Mumbai | D9: East | E9: Office Chair | F9: Furniture | G9: 6 | H9: 7634.15 | I9: 0.15 | J9: 38934.16 | K9: Online
A10: ORD0035 | B10: 45669 | C10: Thane | D10: East | E10: Keyboard | F10: Accessories | G10: 2 | H10: 1137.19 | I10: 0 | J10: 2274.38 | K10: Distributor
A11: ORD0047 | B11: 45670 | C11: Thane | D11: East | E11: USB Drive | F11: Accessories | G11: 8 | H11: 557.11 | I11: 0.15 | J11: 3788.35 | K11: Retail
A12: ORD0172 | B12: 45671 | C12: Nashik | D12: South | E12: Desk | F12: Furniture | G12: 5 | H12: 9999.79 | I12: 0.15 | J12: 42499.11 | K12: Online
A13: ORD0062 | B13: 45672 | C13: Thane | D13: South | E13: Keyboard | F13: Accessories | G13: 8 | H13: 1215.75 | I13: 0.05 | J13: 9239.7 | K13: Online
... A301: ORD0218 | B301: 46022 | C301: Thane | D301: West | E301: Desk | F301: Furniture | G301: 2 | H301: 9160.99 | I301: 0 | J301: 18321.98 | K301: Retail

Sheet Read Me
A1: SALES DATA ANALYSIS DASHBOARD — BEGINNER PROJECT
A2: Project objective | B2: Analyze 300 sample sales transactions and identify sales trends and performance.
A3: Dataset note | B3: This is synthetic practice data, not real company data.
A4: Step 1 — Explore | B4: Open Sales Data. Filter columns and inspect dates, products, categories, regions, and sales channels.
A5: Step 2 — Check quality | B5: Use Data > Remove Duplicates on Order ID only if duplicate IDs exist. Check blank cells and date/number formats.
A6: Step 3 — Add a calculated column (optional) | B6: Add a new column called Gross Sales and use =G2*H2. Revenue already reflects the discount in this sample.
A7: Step 4 — Create PivotTable | B7: Select a cell in Sales Data > Insert > PivotTable > New Worksheet.
A8: Step 5 — Category analysis | B8: Drag Category to Rows and Revenue (₹) to Values. Make sure Values is set to Sum.
A9: Step 6 — Monthly trend | B9: Add a Month column in Sales Data with =TEXT(B2,"mmm") for quick practice, or group Order Date by Months in a PivotTable.
A10: Step 7 — Region analysis | B10: Create a PivotTable with Region in Rows and Revenue (₹) in Values.
A11: Step 8 — Add charts | B11: Select a PivotTable and choose Insert > PivotChart. Use a bar/column chart for category or region; line chart for monthly trends.
A12: Step 9 — Dashboard | B12: Create a new sheet named Dashboard. Add KPI cells for total revenue, total orders, units sold, and average order value.
A13: Useful formulas | B13: Total revenue: =SUM('Sales Data'!J2:J301)
B14: Order count: =COUNTA('Sales Data'!A2:A301)
B15: Units sold: =SUM('Sales Data'!G2:G301)
B16: Average order revenue: =AVERAGE('Sales Data'!J2:J301)
A17: Step 10 — Make interactive | B17: If supported, add slicers to PivotTables for Region, Category, and Sales Channel. Connect slicers to relevant PivotTables.
A18: Interview explanation | B18: I analyzed a sample sales dataset in Excel, checked data quality, summarized revenue by category and region, reviewed trends over time, and designed a dashboard to support business decisions.
A19: Important | B19: Do not claim findings from the sample as real-world company results. Refresh PivotTables after editing the dataset.
